pywebcat/__init__.py
pywebcat/cli.py
pywebcat/utils.py
pywebcat-0.2.1.dist-info/entry_points.txt
pywebcat-0.2.1.dist-info/LICENSE.md
pywebcat-0.2.1.dist-info/WHEEL
pywebcat-0.2.1.dist-info/METADATA
pywebcat-0.2.1.dist-info/RECORD
