Metadata-Version: 2.1
Name: pywebcat
Version: 0.2.1
Summary: Python tool for working with the NOAA NOS Web Camera Applications Testbed (WebCAT)
Home-page: https://github.com/UNCG-DAISY/WebCAT-Utilities
License: MIT
Author: Tomas Beuzen
Author-email: tomas.beuzen@gmail.com
Requires-Python: >=3.7,<4.0
Classifier: License :: OSI Approved :: MIT License
Classifier: Programming Language :: Python :: 3
Classifier: Programming Language :: Python :: 3.7
Classifier: Programming Language :: Python :: 3.8
Requires-Dist: matplotlib (>=3.2.1,<4.0.0)
Requires-Dist: numpy (>=1.18.5,<2.0.0)
Requires-Dist: opencv-python (>=4.2.0,<5.0.0)
Requires-Dist: pandas (>=1.0.4,<2.0.0)
Requires-Dist: tqdm (>=4.46.1,<5.0.0)
Project-URL: Documentation, https://pywebcat.readthedocs.io
Project-URL: Repository, https://github.com/UNCG-DAISY/WebCAT-Utilities
